{
	"uid": "bestxtrackoftheweek",
	"tags": [
		"music"
	],
	"publication_date": "2024-02-24T10:03:02+0000",
	"title": "Best ”XTrack“ of the Week",
	"subtitle": "Les meilleurs sons de la semaine        -       Cover : Teezo Touchdown",
	"text_color": "green",
	"image": null,
	"video_loop": {
		"name": "Teezo Touchdown.mp4",
		"url": "https://x-track-mag.cdn.prismic.io/x-track-mag/52784e67-0856-4fb8-940f-e296ab25dc74_Teezo+Touchdown.mp4",
		"size": "6808960"
	},
	"template": "1: Image + Titre + sous-titre + infos",
	"author": "XTrack Team",
	"internal_link": null,
	"sections": [
		{
			"template": "section-full-text",
			"text": [
				{
					"type": "paragraph",
					"text": "Jungle x Full Crate - Khruangbin - Bloody Civilian - Liam Bailey - Yaadman - Central Cee - Teezo Touchdown - Mystic Marley - Chop Daily x Torann x Skondtrack - Soul Sugar x Leo Carmichael - Cash Cobain RY X - French Montana x Jeremih - PDOT O x Ami Faku - Erika de Casier x Blood Orange & +++ Enjoy",
					"spans": []
				}
			]
		},
		{
			"template": "section-gallery",
			"gallery": [
				{
					"url": "https://images.prismic.io/x-track-mag/d928e21c-7730-4347-8689-87185a94fbe2_Jungle.jpg?auto=compress,format&rect=0,0,1080,1350&w=1024&h=1280",
					"alt": "Jungle",
					"copyright": null,
					"width": 1024,
					"height": 1280,
					"ratio": 0.8
				},
				{
					"url": "https://images.prismic.io/x-track-mag/a785e648-7a02-4921-8362-08ec79846661_Bloody+Civilian+.jpg?auto=compress,format&rect=0,0,1080,1350&w=1024&h=1280",
					"alt": "Bloody Civilian",
					"copyright": null,
					"width": 1024,
					"height": 1280,
					"ratio": 0.8
				},
				{
					"url": "https://images.prismic.io/x-track-mag/d6bba158-ad31-477e-a2f8-ddc10951a909_Liam+Bailey.jpg?auto=compress,format&rect=0,0,1080,1080&w=1024&h=1024",
					"alt": "Liam Bailey.",
					"copyright": null,
					"width": 1024,
					"height": 1024,
					"ratio": 1
				}
			]
		},
		{
			"template": "section-gallery",
			"gallery": [
				{
					"url": "https://images.prismic.io/x-track-mag/34810276-c78a-48bd-b090-41570cd78634_Mystic+Marley.jpg?auto=compress,format&rect=0,0,1080,1350&w=1024&h=1280",
					"alt": "Mystic Marley",
					"copyright": null,
					"width": 1024,
					"height": 1280,
					"ratio": 0.8
				},
				{
					"url": "https://images.prismic.io/x-track-mag/318cad84-ecbd-4303-8ee4-f33abda34a3e_Central+Cee.jpg?auto=compress,format&rect=0,0,1080,1350&w=1024&h=1280",
					"alt": "Central Cee",
					"copyright": null,
					"width": 1024,
					"height": 1280,
					"ratio": 0.8
				},
				{
					"url": "https://images.prismic.io/x-track-mag/b9291825-982f-4858-a4ef-2bc680e9bdd2_khruangbin-Band.jpg?auto=compress,format&rect=0,0,1200,795&w=1024&h=678",
					"alt": null,
					"copyright": null,
					"width": 1024,
					"height": 678,
					"ratio": 1.5103244837758112
				}
			]
		},
		{
			"template": "section-playlist",
			"playlist": [
				{
					"url": "https://www.youtube.com/playlist?list=PLLJkxWPTDgMDdotNZcLvSdBenSFTkLmyP",
					"title": "Best ”XTrack“ of the Week"
				},
				{
					"url": "https://open.spotify.com/playlist/6JTBjrHT8zeNNYSDWuD4GW?si=de79b7bcf52a480f",
					"title": "Best ”XTrack“ of the Week"
				},
				{
					"url": "https://www.deezer.com/fr/playlist/4099699282",
					"title": "Best ”XTrack“ of the Week"
				}
			]
		}
	],
	"description": "Playlist des meilleurs sons de la semaine"
}