{
	"uid": "bestxtrackoftheweek",
	"tags": [
		"music"
	],
	"publication_date": "2024-03-16T18:56:54+0000",
	"title": "Best ”XTrack“ of the Week",
	"subtitle": "Les meilleurs sons de la semaine        -       Cover : Lava La Rue",
	"text_color": "inverted",
	"image": null,
	"video_loop": {
		"name": "Lava La Rue.mp4",
		"url": "https://x-track-mag.cdn.prismic.io/x-track-mag/ZfXk4cmUzjad_Td1_LavaLaRue.mp4",
		"size": "9217144"
	},
	"template": "1: Image + Titre + sous-titre + infos",
	"author": "XTrack Team",
	"internal_link": null,
	"sections": [
		{
			"template": "section-full-text",
			"text": [
				{
					"type": "paragraph",
					"text": "Tierra Whack - Lava La Rue - Chase Chakur - Adi Oasis x Jitwam - Clue Ashavisha Track x Big Yasa x Maandy - Kida Kudz - Galdive - Soul sugar x Jolly Joseph - Don Toliver - Lil Yatchy - Partynextdoor & +++ Enjoy",
					"spans": []
				}
			]
		},
		{
			"template": "section-gallery",
			"gallery": [
				{
					"url": "https://images.prismic.io/x-track-mag/ZfXk4smUzjad_Td2_TierraWhack.jpg?auto=compress,format&rect=0,0,1080,1349&w=1024&h=1279",
					"alt": null,
					"copyright": null,
					"width": 1024,
					"height": 1279,
					"ratio": 0.800625488663018
				},
				{
					"url": "https://images.prismic.io/x-track-mag/ZfXk2smUzjad_Tdr_KidaKudz.jpg?auto=compress,format&rect=0,0,1080,1350&w=1024&h=1280",
					"alt": "Kida Kudz",
					"copyright": null,
					"width": 1024,
					"height": 1280,
					"ratio": 0.8
				},
				{
					"url": "https://images.prismic.io/x-track-mag/ZfXk3MmUzjad_Tdt_AdiOasis.jpg?auto=compress,format&rect=0,0,1080,1079&w=1024&h=1023",
					"alt": "Adi Oasis",
					"copyright": null,
					"width": 1024,
					"height": 1023,
					"ratio": 1.0009775171065494
				}
			]
		},
		{
			"template": "section-gallery",
			"gallery": [
				{
					"url": "https://images.prismic.io/x-track-mag/ZfXk2smUzjad_Tdr_KidaKudz.jpg?auto=compress,format&rect=0,0,1080,1350&w=1024&h=1280",
					"alt": "Kida Kudz",
					"copyright": null,
					"width": 1024,
					"height": 1280,
					"ratio": 0.8
				},
				{
					"url": "https://images.prismic.io/x-track-mag/ZfXk38mUzjad_Tdx_LavaLaRue.jpg?auto=compress,format&rect=0,0,1080,1346&w=1024&h=1276",
					"alt": "Lava La Rue",
					"copyright": null,
					"width": 1024,
					"height": 1276,
					"ratio": 0.8025078369905956
				},
				{
					"url": "https://images.prismic.io/x-track-mag/ZfXk2MmUzjad_Tdp_DonToliver.jpg?auto=compress,format&rect=0,0,1080,1350&w=1024&h=1280",
					"alt": "Don Toliver",
					"copyright": null,
					"width": 1024,
					"height": 1280,
					"ratio": 0.8
				}
			]
		},
		{
			"template": "section-playlist",
			"playlist": [
				{
					"url": "https://www.youtube.com/playlist?list=PLLJkxWPTDgMDdotNZcLvSdBenSFTkLmyP",
					"title": "Best ”XTrack“ of the Week"
				},
				{
					"url": "https://open.spotify.com/playlist/6JTBjrHT8zeNNYSDWuD4GW?si=de79b7bcf52a480f",
					"title": "Best ”XTrack“ of the Week"
				},
				{
					"url": "https://www.deezer.com/fr/playlist/4099699282",
					"title": "Best ”XTrack“ of the Week"
				}
			]
		}
	],
	"description": "Playlist des meilleurs sons de la semaine"
}