{
	"uid": "bestxtrackoftheweek",
	"tags": [
		"music"
	],
	"publication_date": "2024-01-29T15:04:40+0000",
	"title": "Best ”XTrack“ of the Week",
	"subtitle": "Les meilleurs sons de la semaine        -       Cover : Tierra Whack",
	"text_color": "green",
	"image": null,
	"video_loop": {
		"name": "Tierra Whack.mp4",
		"url": "https://x-track-mag.cdn.prismic.io/x-track-mag/41f0c821-22c1-4107-a039-a67bdc09e845_Tierra+Whack.mp4",
		"size": "3682521"
	},
	"template": "1: Image + Titre + sous-titre + infos",
	"author": "XTrack Team",
	"internal_link": null,
	"sections": [
		{
			"template": "section-full-text",
			"text": [
				{
					"type": "paragraph",
					"text": "Jada Kingdom - Tierra Whack - C Kay - Blick Bassy - Protoje - Kelela x Shygirl x JD Reid - Lala &ce - Stefflon Don - Tyla - Asake -  Popcaan - Jack harlow & +++ Enjoy",
					"spans": []
				}
			]
		},
		{
			"template": "section-gallery",
			"gallery": [
				{
					"url": "https://images.prismic.io/x-track-mag/e3b73ecf-a05d-4995-bbd6-dfb815c8d40a_Jada+Kingdom.jpg?auto=compress,format&rect=0,0,1080,1350&w=1024&h=1280",
					"alt": "Jada Kingdom",
					"copyright": null,
					"width": 1024,
					"height": 1280,
					"ratio": 0.8
				},
				{
					"url": "https://images.prismic.io/x-track-mag/b08b1852-a32a-4ad3-9f79-5f46875159de_C+Kay.jpg?auto=compress,format&rect=0,0,1080,1350&w=1024&h=1280",
					"alt": "C Kay",
					"copyright": null,
					"width": 1024,
					"height": 1280,
					"ratio": 0.8
				},
				{
					"url": "https://images.prismic.io/x-track-mag/d2153cd6-032e-4ac7-a844-47c34aed6dce_Tyla++.jpg?auto=compress,format&rect=0,0,930,1060&w=1024&h=1167",
					"alt": "Tyla",
					"copyright": null,
					"width": 1024,
					"height": 1167,
					"ratio": 0.8774635818337618
				}
			]
		},
		{
			"template": "section-gallery",
			"gallery": [
				{
					"url": "https://images.prismic.io/x-track-mag/12b4fd0d-936e-4da6-9ac4-59431db92ad2_Shy+Girl+x+Kelela.jpg?auto=compress,format&rect=0,0,1080,1080&w=1024&h=1024",
					"alt": "Shy Girl x Kelela",
					"copyright": null,
					"width": 1024,
					"height": 1024,
					"ratio": 1
				},
				{
					"url": "https://images.prismic.io/x-track-mag/26c5750d-e720-47d7-8d99-e044d136b982_Protoje.jpg?auto=compress,format&rect=0,0,1612,2015&w=1024&h=1280",
					"alt": "Protoje",
					"copyright": null,
					"width": 1024,
					"height": 1280,
					"ratio": 0.8
				},
				{
					"url": "https://images.prismic.io/x-track-mag/08424b6c-4245-420f-a076-29f7856d7e34_Lala+%26ce.jpg?auto=compress,format&rect=0,0,1264,711&w=1024&h=576",
					"alt": "Lala &ce",
					"copyright": null,
					"width": 1024,
					"height": 576,
					"ratio": 1.7777777777777777
				}
			]
		},
		{
			"template": "section-playlist",
			"playlist": [
				{
					"url": "https://www.youtube.com/playlist?list=PLLJkxWPTDgMDdotNZcLvSdBenSFTkLmyP",
					"title": "Best ”XTrack“ of the Week"
				},
				{
					"url": "https://open.spotify.com/playlist/6JTBjrHT8zeNNYSDWuD4GW?si=de79b7bcf52a480f",
					"title": "Best ”XTrack“ of the Week"
				},
				{
					"url": "https://www.deezer.com/fr/playlist/4099699282",
					"title": "Best ”XTrack“ of the Week"
				}
			]
		}
	],
	"description": "Playlist des meilleurs sons de la semaine"
}