{
	"uid": "bestxtrackoftheweek",
	"tags": [
		"music"
	],
	"publication_date": "2024-09-29T11:24:05+0000",
	"title": "Best ”XTrack“ of the Week",
	"subtitle": "Les meilleurs sons de la semaine - Omah Lay",
	"text_color": "inverted",
	"image": null,
	"video_loop": {
		"name": "Omah Lay.mp4",
		"url": "https://x-track-mag.cdn.prismic.io/x-track-mag/ZvkxFrVsGrYSwG23_OmahLay.mp4",
		"size": "2609490"
	},
	"template": "1: Image + Titre + sous-titre + infos",
	"author": "XTrack Team",
	"internal_link": null,
	"sections": [
		{
			"template": "section-full-text",
			"text": [
				{
					"type": "paragraph",
					"text": "Leon Bridges - Omah Lay - Maz x Antdot x Giton x Layefa - Tekno - Jaz Karis x Juls - Mustafa - Popcann - Lala &ce - The Artist x Vontee the Singer - 4bats x Lil Baby - Michael Kiwannuka - Fousheé - The Cavemen - Jamie xx x Kelsey Lu x John Glacier x Panda Bear - Jungle  - Miraa May - Kali Uchis - +++ Enjoy ",
					"spans": [],
					"direction": "ltr"
				}
			]
		},
		{
			"template": "section-gallery",
			"gallery": [
				{
					"url": "https://images.prismic.io/x-track-mag/ZvkyvrVsGrYSwG3Y_LeonBridges.jpg?auto=format,compress&rect=0,0,1080,1350&w=1024&h=1280",
					"alt": "Leon Bridges",
					"copyright": null,
					"width": 1024,
					"height": 1280,
					"ratio": 0.8
				},
				{
					"url": "https://images.prismic.io/x-track-mag/ZvkyvbVsGrYSwG3X_Layefa.jpg?auto=format,compress&rect=0,0,1080,1296&w=1024&h=1229",
					"alt": "Layefa",
					"copyright": null,
					"width": 1024,
					"height": 1229,
					"ratio": 0.8331977217249796
				},
				{
					"url": "https://images.prismic.io/x-track-mag/Zvkyu7VsGrYSwG3V_Giton.jpg?auto=format,compress&rect=0,0,1080,1350&w=1024&h=1280",
					"alt": "Giton",
					"copyright": null,
					"width": 1024,
					"height": 1280,
					"ratio": 0.8
				}
			]
		},
		{
			"template": "section-gallery",
			"gallery": [
				{
					"url": "https://images.prismic.io/x-track-mag/7cadd287-6bd4-4361-be39-d108791bd67c_Popcaan.png?auto=format,compress&rect=0,0,1080,675&w=1024&h=640",
					"alt": "Popcaan",
					"copyright": null,
					"width": 1024,
					"height": 640,
					"ratio": 1.6
				},
				{
					"url": "https://images.prismic.io/x-track-mag/ZvkyurVsGrYSwG3U_JazKaris.jpg?auto=format,compress&rect=0,0,1080,1350&w=1024&h=1280",
					"alt": "Jaz Karis",
					"copyright": null,
					"width": 1024,
					"height": 1280,
					"ratio": 0.8
				},
				{
					"url": "https://images.prismic.io/x-track-mag/Zvkyt7VsGrYSwG3R_TheArtist.jpg?auto=format,compress&rect=0,0,1080,1349&w=1024&h=1279",
					"alt": "The Artist",
					"copyright": null,
					"width": 1024,
					"height": 1279,
					"ratio": 0.800625488663018
				}
			]
		},
		{
			"template": "section-playlist",
			"playlist": [
				{
					"url": "https://www.youtube.com/playlist?list=PLLJkxWPTDgMDdotNZcLvSdBenSFTkLmyP",
					"title": "Best ”XTrack“ of the Week"
				},
				{
					"url": "https://open.spotify.com/playlist/6JTBjrHT8zeNNYSDWuD4GW?si=de79b7bcf52a480f",
					"title": "Best ”XTrack“ of the Week"
				},
				{
					"url": "https://www.deezer.com/fr/playlist/4099699282",
					"title": "Best ”XTrack“ of the Week"
				}
			]
		}
	],
	"description": "Playlist des meilleurs sons de la semaine"
}