{
	"uid": "hiphopsoul",
	"tags": [
		"music"
	],
	"publication_date": "2026-04-12T08:37:49+0000",
	"title": "Hip Hop RnB",
	"subtitle": "Happy Crossover - Outkast on Cover",
	"text_color": "inverted",
	"image": null,
	"video_loop": {
		"name": "Outkast  .jpg",
		"url": "https://images.prismic.io/x-track-mag/aNe1J55xUNkB1LDu_Outkast.jpg?auto=format,compress?auto=compress,format"
	},
	"template": "1: Image + Titre + sous-titre + infos",
	"author": "XTrack Team",
	"internal_link": null,
	"sections": [
		{
			"template": "section-full-text",
			"text": [
				{
					"type": "paragraph",
					"text": "D'Angelo + Busta Rhymes x Erykah Badu x Mariah Carey x Flipmode Squad + Lenny Kravitz x jay Z + Outkast + Slum Village + Janet Jackson x QTip x Joni Mitchel +  Kanye West x Paul Wall x GLC + Dr Dre x Snoop Dog + Blackstreet x Dr Dre x Queen Pen + Ms Lauryn Hill + Guru x Paul Ferguson x Baby + Mos Def + Lucy Pearl + 2Pac + Dr Dre + Roger + Method Man x Mary J Blige + N.E.R.D. + Pharrell Williams x Kanye West & ++++ Enjoy",
					"spans": [],
					"direction": "ltr"
				}
			]
		},
		{
			"template": "section-gallery",
			"gallery": [
				{
					"url": "https://images.prismic.io/x-track-mag/8297802a-5ca6-4800-a95c-8d810360abfd_Erykah+Badu.jpg?auto=format,compress&rect=0,0,1133,715&w=1024&h=646",
					"alt": "Erykah Badu",
					"copyright": null,
					"width": 1024,
					"height": 646,
					"ratio": 1.585139318885449
				},
				{
					"url": "https://images.prismic.io/x-track-mag/aNe19p5xUNkB1LD0_Guru.jpg?auto=format,compress&rect=0,0,1487,1500&w=1024&h=1033",
					"alt": "Guru",
					"copyright": null,
					"width": 1024,
					"height": 1033,
					"ratio": 0.9912875121006777
				},
				{
					"url": "https://images.prismic.io/x-track-mag/672c22ee-c789-43cf-bee0-d599664ace95_Lauryn+Hill.jpg?auto=format,compress&rect=0,0,1499,1000&w=1024&h=683",
					"alt": "Lauryn Hill",
					"copyright": null,
					"width": 1024,
					"height": 683,
					"ratio": 1.499267935578331
				}
			]
		},
		{
			"template": "section-gallery",
			"gallery": [
				{
					"url": "https://images.prismic.io/x-track-mag/ZpJDfR5LeNNTxITT_PharrellWilliamsxKanyeWest.jpg?auto=format,compress&rect=0,0,1100,620&w=1024&h=577",
					"alt": "Pharrell Williams x Kanye West",
					"copyright": null,
					"width": 1024,
					"height": 577,
					"ratio": 1.7746967071057191
				},
				{
					"url": "https://images.prismic.io/x-track-mag/Zt2RShoQrfVKl0bH_JanetJackson.jpg?auto=format,compress&rect=0,0,1024,1004&w=1024&h=1004",
					"alt": "Janet Jackson",
					"copyright": null,
					"width": 1024,
					"height": 1004,
					"ratio": 1.0199203187250996
				},
				{
					"url": "https://images.prismic.io/x-track-mag/3c5be5e7-44da-485c-85a0-15f16dd3019f_2pac.jpg?auto=format,compress&rect=0,0,1280,720&w=1024&h=576",
					"alt": "2pac",
					"copyright": null,
					"width": 1024,
					"height": 576,
					"ratio": 1.7777777777777777
				}
			]
		},
		{
			"template": "section-playlist",
			"playlist": [
				{
					"url": "https://www.youtube.com/playlist?list=PLLJkxWPTDgMC1CzGVtkqvVDwuS6EABM_A",
					"title": "Hip Hop RnB"
				},
				{
					"url": "https://open.spotify.com/playlist/18sF2iGVaxde2EZLDzXgx2?si=420b41bd69074f92",
					"title": "Hip Hop RnB"
				},
				{
					"url": "https://www.deezer.com/fr/playlist/4930107344",
					"title": "Hip Hop RnB"
				}
			]
		}
	],
	"description": "Nice & Happy"
}