{
	"uid": "new-romance",
	"tags": [
		"music"
	],
	"publication_date": "2024-10-05T16:10:16+0000",
	"title": "New Romance",
	"subtitle": "100% Chill Vibes - Nia Smith on Cover",
	"text_color": "inverted",
	"image": null,
	"video_loop": {
		"name": "Nia Smith.mp4",
		"url": "https://x-track-mag.cdn.prismic.io/x-track-mag/Zt2bYxoQrfVKl0dZ_NiaSmith.mp4",
		"size": "12726398"
	},
	"template": "1: Image + Titre + sous-titre + infos",
	"author": "XTrack Team",
	"internal_link": null,
	"sections": [
		{
			"template": "section-full-text",
			"text": [
				{
					"type": "paragraph",
					"text": " Jungle x Full Crate - Hope Tala - 4Batz x Lil Baby - Victony x SAINt JHN - Michael Kiwanuka - Mustafa - Leon Bridges - Nia Smith - Kali Uchis - Judeline - The Cavemen - Nep - Ezéchiel Pailhes - Patchowrks x Pat Kala - Saint Levant x MC Abdul - Chaton - Cleo Sol - Teni - Chiiild x Shungudzo - Raveena x Jpegmafia - Babeheaven - Khruangbin  & +++ enjoy",
					"spans": [],
					"direction": "ltr"
				}
			]
		},
		{
			"template": "section-gallery",
			"gallery": [
				{
					"url": "https://images.prismic.io/x-track-mag/f8d703b6-270e-4ec5-b469-65423cccca7e_Victony.jpg?auto=format,compress&rect=0,0,1080,1350&w=1024&h=1280",
					"alt": "Victony",
					"copyright": null,
					"width": 1024,
					"height": 1280,
					"ratio": 0.8
				},
				{
					"url": "https://images.prismic.io/x-track-mag/ZrshBUaF0TcGI4tE_KaliUchis.jpg?auto=format,compress&rect=0,0,1080,1350&w=1024&h=1280",
					"alt": "Kali Uchis",
					"copyright": null,
					"width": 1024,
					"height": 1280,
					"ratio": 0.8
				},
				{
					"url": "https://images.prismic.io/x-track-mag/ZtxoQxoQrfVKlz7__LeonBridges.jpg?auto=format,compress&rect=0,0,1080,1350&w=1024&h=1280",
					"alt": "Leon Bridges",
					"copyright": null,
					"width": 1024,
					"height": 1280,
					"ratio": 0.8
				}
			]
		},
		{
			"template": "section-gallery",
			"gallery": [
				{
					"url": "https://images.prismic.io/x-track-mag/6a629759-d10d-4926-95b0-33b65a47d81f_Mustafa.jpg?auto=format,compress&rect=0,0,1080,1349&w=1024&h=1279",
					"alt": "Mustafa",
					"copyright": null,
					"width": 1024,
					"height": 1279,
					"ratio": 0.800625488663018
				},
				{
					"url": "https://images.prismic.io/x-track-mag/Zsm3g0aF0TcGJXzd_HopeTala.jpg?auto=format,compress&rect=0,0,1080,1080&w=1024&h=1024",
					"alt": "Hope Tala",
					"copyright": null,
					"width": 1024,
					"height": 1024,
					"ratio": 1
				},
				{
					"url": "https://images.prismic.io/x-track-mag/83f5751e-8bd7-410a-896f-83491939dc29_Jungle.jpg?auto=format,compress&rect=0,0,1080,1080&w=1024&h=1024",
					"alt": "Jungle",
					"copyright": null,
					"width": 1024,
					"height": 1024,
					"ratio": 1
				}
			]
		},
		{
			"template": "section-playlist",
			"playlist": [
				{
					"url": "https://www.youtube.com/playlist?list=PLLJkxWPTDgMDMUA9bisL8vy_ZtGzDX7Dd",
					"title": "New romance"
				},
				{
					"url": "https://open.spotify.com/playlist/18sF2iGVaxde2EZLDzXgx2?si=4ad8031353d14874",
					"title": "New romance"
				},
				{
					"url": "https://www.deezer.com/fr/playlist/5281964882",
					"title": "New romance"
				}
			]
		}
	],
	"description": "Playlist Chill, Cool, Love"
}